{"__schema":{"types":[{"kind":"UNION","name":"SearchResultData","possibleTypes":[{"name":"ProductSearchResultData"},{"name":"PhysicalProductSearchResultData"}]},{"kind":"INTERFACE","name":"Node","possibleTypes":[{"name":"PushNotificationReceipt"},{"name":"UserPushNotification"},{"name":"UserPushNotificationInterest"},{"name":"CustomerDetail"},{"name":"StylePreferences"},{"name":"Location"},{"name":"WarehouseLocation"},{"name":"WarehouseLocationConstraint"},{"name":"Category"},{"name":"ProductMaterialCategory"},{"name":"ProductModel"},{"name":"Size"},{"name":"TopSize"},{"name":"BottomSize"},{"name":"Color"},{"name":"ProductSeason"},{"name":"Season"},{"name":"Tag"},{"name":"ProductFunction"},{"name":"Package"},{"name":"Label"},{"name":"PackageTransitEvent"},{"name":"ReservationFeedback"},{"name":"ProductVariantFeedback"},{"name":"ProductVariantFeedbackQuestion"},{"name":"BillingInfo"},{"name":"PaymentPlan"},{"name":"BagItem"},{"name":"CustomerMembership"},{"name":"PauseRequest"},{"name":"CustomerAdmissionsData"},{"name":"Collection"},{"name":"ProductRequest"},{"name":"HomepageProductRail"},{"name":"FitPicReport"},{"name":"InterestedUser"},{"name":"ReservationReceipt"},{"name":"ReservationReceiptItem"},{"name":"RecentlyViewedProduct"},{"name":"ProductVariantWant"},{"name":"ActiveAdminUser"},{"name":"CollectionGroup"},{"name":"EmailReceipt"},{"name":"SmsReceipt"},{"name":"SyncTiming"}]},{"kind":"UNION","name":"HomepageResult","possibleTypes":[{"name":"Product"},{"name":"Collection"},{"name":"Brand"}]}]}}